DriveX/__init__.py
DriveX/core/__init__.py
DriveX/core/Authenticator/Authenticator.py
DriveX/core/Authenticator/__init__.py
DriveX/core/FileManager/FileManager.py
DriveX/core/FileManager/__init__.py
DriveX/core/FolderManager/FolderManager.py
DriveX/core/FolderManager/__init__.py
DriveX/core/GoogleDriveAPI/GoogleDriveAPI.py
DriveX/core/GoogleDriveAPI/__init__.py
DriveX/core/ServiceBuilder/ServiceBuilder.py
DriveX/core/ServiceBuilder/__init__.py
DriveX/error/ERR.py
DriveX/error/__init__.py
DriveX/error/error.py
DriveX-0.1.dist-info/LICENSE
DriveX-0.1.dist-info/METADATA
DriveX-0.1.dist-info/WHEEL
DriveX-0.1.dist-info/top_level.txt
DriveX-0.1.dist-info/RECORD
