Metadata-Version: 2.1
Name: DriveX
Version: 0.1
Summary: DriveX library to connect and work with Google Drive!
Home-page: https://github.com/Sepehr0Day/DriveX/
Author: Sepehr
Author-email: sphrz2324@gmail.com
License: MIT
License-File: LICENSE
Requires-Dist: google-auth-oauthlib
Requires-Dist: google-auth
